srclient/__init__.py
srclient/api.py
srclient/manager.py
srclient/webcrawler.py
srclient-0.0.1.data/scripts/short-report-client
srclient-0.0.1.dist-info/DESCRIPTION.rst
srclient-0.0.1.dist-info/METADATA
srclient-0.0.1.dist-info/RECORD
srclient-0.0.1.dist-info/WHEEL
srclient-0.0.1.dist-info/metadata.json
srclient-0.0.1.dist-info/top_level.txt
