Metadata-Version: 2.0
Name: srclient
Version: 0.0.1
Summary: A small client for short-report.
Home-page: https://github.com/axju/short-report-client
Author: Axel Juraske
Author-email: axel.juraske@short-report.de
License: MIT
Keywords: REST client coreapi short report
Platform: UNKNOWN
Classifier: Development Status :: 3 - Alpha
Classifier: License :: OSI Approved :: MIT License
Classifier: Programming Language :: Python :: 3.7
Classifier: Topic :: Communications
Classifier: Topic :: Internet :: WWW/HTTP
Requires-Dist: argparse
Requires-Dist: bs4
Requires-Dist: coreapi
Requires-Dist: requests
